b2constsites/__init__.py
b2constsites/b2constsites.py
b2constsites/run_b2constsites.py
b2constsites-0.3.3.dist-info/entry_points.txt
b2constsites-0.3.3.dist-info/LICENSE
b2constsites-0.3.3.dist-info/WHEEL
b2constsites-0.3.3.dist-info/METADATA
b2constsites-0.3.3.dist-info/RECORD
