Metadata-Version: 2.1
Name: b2constsites
Version: 0.3.3
Summary: Generate an appropriate data tag to add constant sites to your BEAST2 XML
Home-page: https://github.com/andersgs/beast2_constsites/
License: UNKNOWN
Author: Anders Goncalves da Silva
Author-email: andersgs@gmail.com
Requires-Python: >=3.6
Classifier: License :: OSI Approved :: GNU General Public License v3 or later (GPLv3+)
Classifier: Development Status :: 4 - Beta
Classifier: Topic :: Scientific/Engineering :: Bio-Informatics
Classifier: Intended Audience :: Science/Research
Requires-Dist: biopython (>=1.70)
Requires-Dist: pyvcf (>=0.6.8)
